{
  "web":{
    "client_id":"733953641690-mveq478ua38qgekn7nnknjl1a4hm74tg.apps.googleusercontent.com",
    "project_id":"pokedex-218315",
    "auth_uri":"https://accounts.google.com/o/oauth2/auth",
    "token_uri":"https://www.googleapis.com/oauth2/v3/token",
    "auth_provider_x509_cert_url":"https://www.googleapis.com/oauth2/v1/certs",
    "client_secret":"wgzvA2rSMCA-Nt6HRj2bQVsE",
    "redirect_uris":["http://localhost:8000/pokemon/"],
    "javascript_origins":["http://localhost:8000"]
  }
}
